logcleanaudit/__init__.py
logcleanaudit/audit_decorators.py
logcleanaudit/custom_logger.py
logcleanaudit/logger_ansi_codes.py
logcleanaudit-0.1.3.dist-info/METADATA
logcleanaudit-0.1.3.dist-info/WHEEL
logcleanaudit-0.1.3.dist-info/top_level.txt
logcleanaudit-0.1.3.dist-info/RECORD
