Metadata-Version: 2.1
Name: logcleanaudit
Version: 0.1.3
Summary: A simple and efficient decorator-based package for auditing and debugging Python programs
Home-page: https://github.com/8bytesword/logcleanaudit
Author: 8ByteSword
Author-email: 8bytesword@gmail.com
License: UNKNOWN
Platform: UNKNOWN
Classifier: Development Status :: 3 - Alpha
Classifier: Intended Audience :: Developers
Classifier: License :: OSI Approved :: MIT License
Classifier: Programming Language :: Python :: 3
Classifier: Programming Language :: Python :: 3.6
Classifier: Programming Language :: Python :: 3.7
Classifier: Programming Language :: Python :: 3.8
Classifier: Programming Language :: Python :: 3.9
Requires-Dist: colorama
Requires-Dist: coloredlogs
